py_undefined/__init__.py
py_undefined/py.typed
py_undefined-0.1.7.dist-info/LICENSE
py_undefined-0.1.7.dist-info/WHEEL
py_undefined-0.1.7.dist-info/METADATA
py_undefined-0.1.7.dist-info/RECORD
