Metadata-Version: 2.1
Name: py-undefined
Version: 0.1.7
Summary: Provides an Undefined constant.
Home-page: https://gitlab.com/mburkard/py-undefined
License: Apache-2.0
Author: Matthew Burkard
Author-email: matthew@gburkard.cloud
Requires-Python: >=3.9,<4.0
Classifier: Intended Audience :: Developers
Classifier: License :: OSI Approved :: Apache Software License
Classifier: Programming Language :: Python :: 3
Classifier: Programming Language :: Python :: 3.10
Classifier: Programming Language :: Python :: 3.11
Classifier: Programming Language :: Python :: 3.9
Classifier: Topic :: Software Development
Classifier: Topic :: Software Development :: Libraries
Classifier: Topic :: Software Development :: Libraries :: Python Modules
Classifier: Typing :: Typed
Requires-Dist: typing-extensions (>=4.9.0,<5.0.0)
Project-URL: Repository, https://gitlab.com/mburkard/py-undefined
